[
    {
        "muid": "1234-abcd-5678",
        "option": [],
        "history": [],
        "star": [],
        "my_feed": [],
        "my_comment": [],
        "active_feed": [],
        "feed_key": 0,
        "comment_key": 0
    },
    {
        "muid": "5678-efgh-1234",
        "option": [],
        "history": [],
        "star": [],
        "my_feed": [],
        "my_comment": [],
        "active_feed": [],
        "feed_key": 0,
        "comment_key": 0
    },
    {
        "muid": "abcd-1234-5678",
        "option": [],
        "history": [],
        "star": [
            "1",
            "2",
            "3",
            "4"
        ],
        "my_feed": [
            "1",
            "2",
            "3",
            "4",
            "5",
            "6",
            "7",
            "8",
            "9"
        ],
        "my_comment": [
            "2-20241001195033"
        ],
        "active_feed": [
            "1",
            "2",
            "5",
            "6",
            "7",
            "8",
            "16"
        ],
        "feed_key": 0,
        "comment_key": 0
    },
    {
        "muid": "ijkl-9876-mnop",
        "option": [],
        "history": [],
        "star": [],
        "my_feed": [],
        "my_comment": [],
        "active_feed": [],
        "feed_key": 0,
        "comment_key": 0
    },
    {
        "muid": "qrst-6543-uvwx",
        "option": [],
        "history": [],
        "star": [],
        "my_feed": [],
        "my_comment": [],
        "active_feed": [],
        "feed_key": 0,
        "comment_key": 0
    },
    {
        "muid": "yzab-1357-cdef",
        "option": [],
        "history": [],
        "star": [],
        "my_feed": [],
        "my_comment": [],
        "active_feed": [],
        "feed_key": 0,
        "comment_key": 0
    },
    {
        "muid": "ghij-2468-klmn",
        "option": [],
        "history": [],
        "star": [],
        "my_feed": [],
        "my_comment": [],
        "active_feed": [],
        "feed_key": 0,
        "comment_key": 0
    },
    {
        "muid": "opqr-3698-stuv",
        "option": [],
        "history": [],
        "star": [],
        "my_feed": [],
        "my_comment": [],
        "active_feed": [],
        "feed_key": 0,
        "comment_key": 0
    },
    {
        "muid": "wxyz-7531-abcd",
        "option": [],
        "history": [],
        "star": [],
        "my_feed": [],
        "my_comment": [],
        "active_feed": [],
        "feed_key": 0,
        "comment_key": 0
    },
    {
        "muid": "mnop-9876-qrst",
        "option": [],
        "history": [],
        "star": [],
        "my_feed": [],
        "my_comment": [],
        "active_feed": [],
        "feed_key": 0,
        "comment_key": 0
    },
    {
        "muid": "abcd-4321-wxyz",
        "option": [],
        "history": [],
        "star": [],
        "my_feed": [],
        "my_comment": [],
        "active_feed": [],
        "feed_key": 0,
        "comment_key": 0
    },
    {
        "muid": "efgh-8765-ijkl",
        "option": [],
        "history": [],
        "star": [],
        "my_feed": [],
        "my_comment": [],
        "active_feed": [],
        "feed_key": 0,
        "comment_key": 0
    },
    {
        "muid": "qrst-2109-uvwx",
        "option": [],
        "history": [],
        "star": [],
        "my_feed": [],
        "my_comment": [],
        "active_feed": [],
        "feed_key": 0,
        "comment_key": 0
    },
    {
        "muid": "uvwx-1098-yzab",
        "option": [],
        "history": [],
        "star": [],
        "my_feed": [],
        "my_comment": [],
        "active_feed": [],
        "feed_key": 0,
        "comment_key": 0
    },
    {
        "muid": "klmn-5432-opqr",
        "option": [],
        "history": [],
        "star": [],
        "my_feed": [],
        "my_comment": [],
        "active_feed": [],
        "feed_key": 0,
        "comment_key": 0
    },
    {
        "muid": "abcd-5678-efgh",
        "option": [],
        "history": [],
        "star": [],
        "my_feed": [],
        "my_comment": [],
        "active_feed": [],
        "feed_key": 0,
        "comment_key": 0
    },
    {
        "muid": "mnop-1122-wxyz",
        "option": [],
        "history": [],
        "star": [],
        "my_feed": [],
        "my_comment": [],
        "active_feed": [],
        "feed_key": 0,
        "comment_key": 0
    },
    {
        "muid": "qrst-3344-uvwx",
        "option": [],
        "history": [],
        "star": [],
        "my_feed": [],
        "my_comment": [],
        "active_feed": [],
        "feed_key": 0,
        "comment_key": 0
    }
]